mango/__init__.py
mango/constants.py
mango_act-0.0.0.dist-info/LICENSE
mango_act-0.0.0.dist-info/METADATA
mango_act-0.0.0.dist-info/WHEEL
mango_act-0.0.0.dist-info/top_level.txt
mango_act-0.0.0.dist-info/RECORD
