Metadata-Version: 2.1
Name: mango-act
Version: 0.0.0
Summary: A Python library based on the papers of Donald Mango
Home-page: https://github.com/genedan/mango
Author: Gene Dan
Author-email: genedan@gmail.com
Project-URL: Documentation, https://genedan.com/mango/docs
Classifier: Programming Language :: Python :: 3.10
Classifier: License :: OSI Approved :: GNU General Public License v3 (GPLv3)
Classifier: Operating System :: POSIX :: Linux
Requires-Python: >=3.10.0
License-File: LICENSE
